monkey/__init__.py
monkey/crawler/__init__.py
monkey/crawler/crawlers/__init__.py
monkey/crawler/crawlers/odbc_crawler.py
monkey.crawler.pyodbc-0.0.1.dev1.dist-info/LICENSE.txt
monkey.crawler.pyodbc-0.0.1.dev1.dist-info/METADATA
monkey.crawler.pyodbc-0.0.1.dev1.dist-info/WHEEL
monkey.crawler.pyodbc-0.0.1.dev1.dist-info/top_level.txt
monkey.crawler.pyodbc-0.0.1.dev1.dist-info/RECORD
